pglive/.DS_Store
pglive/__init__.py
pglive/examples_pyqt5/__init__.py
pglive/examples_pyqt5/all_plot_types.py
pglive/examples_pyqt5/axis.py
pglive/examples_pyqt5/candlestick_plot.py
pglive/examples_pyqt5/categorized_bar_plot.py
pglive/examples_pyqt5/crop_offset_to_data.py
pglive/examples_pyqt5/crosshair.py
pglive/examples_pyqt5/designer_example/__init__.py
pglive/examples_pyqt5/designer_example/main_example.py
pglive/examples_pyqt5/designer_example/win_template.py
pglive/examples_pyqt5/designer_example/win_template.ui
pglive/examples_pyqt5/heatmap_plot.py
pglive/examples_pyqt5/horizontal_bar_plot.py
pglive/examples_pyqt5/leading_line.py
pglive/examples_pyqt5/line_plot.py
pglive/examples_pyqt5/live_plot_range.py
pglive/examples_pyqt5/one_plot_multiple_plot_rates.py
pglive/examples_pyqt5/pause_resume.py
pglive/examples_pyqt5/plot_rate.py
pglive/examples_pyqt5/scatter_plot.py
pglive/examples_pyqt5/update_rate.py
pglive/examples_pyqt5/vertical_bar_plot.py
pglive/examples_pyqt5/vertical_bar_plot_color.py
pglive/examples_pyqt6/__init__.py
pglive/examples_pyqt6/all_plot_types.py
pglive/examples_pyqt6/axis.py
pglive/examples_pyqt6/candlestick_plot.py
pglive/examples_pyqt6/categorized_bar_plot.py
pglive/examples_pyqt6/crop_offset_to_data.py
pglive/examples_pyqt6/crosshair.py
pglive/examples_pyqt6/designer_example/__init__.py
pglive/examples_pyqt6/designer_example/main_example.py
pglive/examples_pyqt6/designer_example/win_template.py
pglive/examples_pyqt6/designer_example/win_template.ui
pglive/examples_pyqt6/heatmap_plot.py
pglive/examples_pyqt6/horizontal_bar_plot.py
pglive/examples_pyqt6/leading_line.py
pglive/examples_pyqt6/line_plot.py
pglive/examples_pyqt6/live_plot_range.py
pglive/examples_pyqt6/one_plot_multiple_plot_rates.py
pglive/examples_pyqt6/pause_resume.py
pglive/examples_pyqt6/plot_rate.py
pglive/examples_pyqt6/scatter_plot.py
pglive/examples_pyqt6/update_rate.py
pglive/examples_pyqt6/vertical_bar_plot.py
pglive/examples_pyqt6/vertical_bar_plot_color.py
pglive-0.9.0.dist-info/LICENSE
pglive-0.9.0.dist-info/METADATA
pglive-0.9.0.dist-info/WHEEL
pglive-0.9.0.dist-info/RECORD
