Metadata-Version: 2.3
Name: pglive
Version: 0.9.0
Summary: Live plot for PyqtGraph
License: MIT
Keywords: pyqtgraph,realtime,live,plotting,pyqt5,pyqt6,pyside6
Author: Martin Domaracky
Author-email: domarm@comat.sk
Requires-Python: >=3.11,<3.14
Classifier: Intended Audience :: Science/Research
Classifier: License :: OSI Approved :: MIT License
Classifier: Natural Language :: English
Classifier: Operating System :: OS Independent
Classifier: Programming Language :: Python :: 3
Classifier: Programming Language :: Python :: 3.11
Classifier: Programming Language :: Python :: 3.12
Classifier: Programming Language :: Python :: 3.13
Classifier: Topic :: Software Development :: Libraries
Requires-Dist: numpy (>=2.3.0,<3.0.0)
Requires-Dist: pyqtgraph (>=0.13.3,<0.14.0)
Project-URL: Homepage, https://github.com/domarm-comat/pglive
Project-URL: Repository, https://github.com/domarm-comat/pglive
